[{"Location": "Off Upper Park Road in Bidwell Park, Chico", "Started": "2024-07-24T14:52:43Z", "AcresBurned": 429603.0, "Latitude": 39.7789, "Longitude": -121.76168, "Url": "https://www.fire.ca.gov/incidents/2024/7/24/park-fire/"}, {"Location": "West of Homers Nose Grove, Sequoia National Park", "Started": "2024-08-03T08:05:39Z", "AcresBurned": 14099.0, "Latitude": 36.38857, "Longitude": -118.768, "Url": "https://www.fire.ca.gov/incidents/2024/8/3/coffee-pot-fire/"}, {"Location": "Baseline street and Alpine street, Highland ", "Started": "2024-09-05T18:33:57Z", "AcresBurned": 39231.6, "Latitude": 34.121119, "Longitude": -117.154705, "Url": "https://www.fire.ca.gov/incidents/2024/9/5/line-fire/"}, {"Location": "Camp Bonita Road, East of Camp Williams", "Started": "2024-09-08T14:12:21Z", "AcresBurned": 54795.0, "Latitude": 34.2396, "Longitude": -117.7625, "Url": "https://www.fire.ca.gov/incidents/2024/9/8/bridge-fire/"}, {"Location": "Trabuco Canyon and Rose Canyon, Trabuco Canyon", "Started": "2024-09-09T13:21:00Z", "AcresBurned": 23519.0, "Latitude": 33.6676762, "Longitude": -117.566221, "Url": "https://www.fire.ca.gov/incidents/2024/9/9/airport-fire/"}]